holoeye_embedded/__init__.py
holoeye_embedded/__meta__.py
holoeye_embedded-1.0.2.dist-info/LICENSE
holoeye_embedded-1.0.2.dist-info/METADATA
holoeye_embedded-1.0.2.dist-info/WHEEL
holoeye_embedded-1.0.2.dist-info/top_level.txt
holoeye_embedded-1.0.2.dist-info/RECORD
